binny/__init__.py
binny/binny.py
binny/general_helpers.py
binny-0.6.2.dist-info/LICENSE.txt
binny-0.6.2.dist-info/METADATA
binny-0.6.2.dist-info/WHEEL
binny-0.6.2.dist-info/top_level.txt
binny-0.6.2.dist-info/RECORD
